diana_client/__init__.py
diana_client/client.py
diana_client/utils.py
diana_client/version.py
diana_client-0.2.3.dist-info/METADATA
diana_client-0.2.3.dist-info/WHEEL
diana_client-0.2.3.dist-info/RECORD
