Metadata-Version: 2.1
Name: diana-client
Version: 0.2.3
Summary: A python based DIANA Client for interacting with the DIANA server with higher level apis.
Author: Hamada Gasmallah
Author-email: hamada@distributive.network
Requires-Python: >=3.9,<4.0
Classifier: Programming Language :: Python :: 3
Classifier: Programming Language :: Python :: 3.9
Classifier: Programming Language :: Python :: 3.10
Classifier: Programming Language :: Python :: 3.11
Classifier: Programming Language :: Python :: 3.12
Requires-Dist: opencv-python (>=4.9.0.80,<5.0.0.0)
